[
  {
    "date": "2026-07-18",
    "status": "present",
    "is_late": false,
    "is_early_leave": false,
    "expected_start_time": "08:00",
    "expected_end_time": "16:30",
    "source": "legacy",
    "first_punch_in": "2026-07-18T07:50:21",
    "last_punch_out": "2026-07-18T16:30:43",
    "total_work_seconds": 31222
  },
  {
    "date": "2026-07-17",
    "status": "present",
    "is_late": false,
    "is_early_leave": false,
    "expected_start_time": "08:00",
    "expected_end_time": "16:30",
    "source": "legacy",
    "first_punch_in": "2026-07-17T07:47:17",
    "last_punch_out": "2026-07-17T16:32:39",
    "total_work_seconds": 31522
  },
  {
    "date": "2026-07-16",
    "status": "present",
    "is_late": false,
    "is_early_leave": false,
    "expected_start_time": "08:00",
    "expected_end_time": "16:30",
    "source": "legacy",
    "first_punch_in": "2026-07-16T07:48:02",
    "last_punch_out": "2026-07-16T16:30:14",
    "total_work_seconds": 31332
  },
  {
    "date": "2026-07-15",
    "status": "present",
    "is_late": false,
    "is_early_leave": false,
    "expected_start_time": "08:00",
    "expected_end_time": "16:30",
    "source": "legacy",
    "first_punch_in": "2026-07-15T07:48:44",
    "last_punch_out": "2026-07-15T16:34:12",
    "total_work_seconds": 31528
  },
  {
    "date": "2026-07-14",
    "status": "present",
    "is_late": false,
    "is_early_leave": false,
    "expected_start_time": "08:00",
    "expected_end_time": "16:30",
    "source": "legacy",
    "first_punch_in": "2026-07-14T07:48:09",
    "last_punch_out": "2026-07-14T16:30:26",
    "total_work_seconds": 31337
  },
  {
    "date": "2026-07-13",
    "status": "present",
    "is_late": false,
    "is_early_leave": false,
    "expected_start_time": "08:00",
    "expected_end_time": "16:30",
    "source": "legacy",
    "first_punch_in": "2026-07-13T07:46:45",
    "last_punch_out": "2026-07-13T16:30:05",
    "total_work_seconds": 31400
  },
  {
    "date": "2026-07-11",
    "status": "present",
    "is_late": false,
    "is_early_leave": false,
    "expected_start_time": "08:00",
    "expected_end_time": "16:30",
    "source": "legacy",
    "first_punch_in": "2026-07-11T07:53:14",
    "last_punch_out": "2026-07-11T16:32:28",
    "total_work_seconds": 31154
  },
  {
    "date": "2026-07-10",
    "status": "present",
    "is_late": true,
    "is_early_leave": false,
    "expected_start_time": "08:00",
    "expected_end_time": "16:30",
    "source": "legacy",
    "first_punch_in": "2026-07-10T08:18:47",
    "last_punch_out": "2026-07-10T16:30:04",
    "total_work_seconds": 29477
  },
  {
    "date": "2026-07-09",
    "status": "present",
    "is_late": false,
    "is_early_leave": false,
    "expected_start_time": "08:00",
    "expected_end_time": "16:30",
    "source": "legacy",
    "first_punch_in": "2026-07-09T07:54:07",
    "last_punch_out": "2026-07-09T16:30:15",
    "total_work_seconds": 30968
  },
  {
    "date": "2026-07-08",
    "status": "present",
    "is_late": false,
    "is_early_leave": false,
    "expected_start_time": "08:00",
    "expected_end_time": "16:30",
    "source": "legacy",
    "first_punch_in": "2026-07-08T07:47:03",
    "last_punch_out": "2026-07-08T16:30:48",
    "total_work_seconds": 31425
  },
  {
    "date": "2026-07-07",
    "status": "present",
    "is_late": false,
    "is_early_leave": false,
    "expected_start_time": "08:00",
    "expected_end_time": "16:30",
    "source": "legacy",
    "first_punch_in": "2026-07-07T07:51:38",
    "last_punch_out": "2026-07-07T16:31:33",
    "total_work_seconds": 31195
  },
  {
    "date": "2026-07-06",
    "status": "present",
    "is_late": false,
    "is_early_leave": false,
    "expected_start_time": "08:00",
    "expected_end_time": "16:30",
    "source": "legacy",
    "first_punch_in": "2026-07-06T07:38:36",
    "last_punch_out": "2026-07-06T16:34:38",
    "total_work_seconds": 32162
  },
  {
    "date": "2026-07-04",
    "status": "present",
    "is_late": false,
    "is_early_leave": false,
    "expected_start_time": "08:00",
    "expected_end_time": "16:30",
    "source": "legacy",
    "first_punch_in": "2026-07-04T07:39:36",
    "last_punch_out": "2026-07-04T16:37:01",
    "total_work_seconds": 32245
  },
  {
    "date": "2026-07-03",
    "status": "present",
    "is_late": false,
    "is_early_leave": false,
    "expected_start_time": "08:00",
    "expected_end_time": "16:30",
    "source": "legacy",
    "first_punch_in": "2026-07-03T07:33:46",
    "last_punch_out": "2026-07-03T16:33:23",
    "total_work_seconds": 32377
  },
  {
    "date": "2026-07-02",
    "status": "present",
    "is_late": false,
    "is_early_leave": false,
    "expected_start_time": "08:00",
    "expected_end_time": "16:30",
    "source": "legacy",
    "first_punch_in": "2026-07-02T07:39:19",
    "last_punch_out": "2026-07-02T16:35:51",
    "total_work_seconds": 32192
  },
  {
    "date": "2026-07-01",
    "status": "present",
    "is_late": true,
    "is_early_leave": false,
    "expected_start_time": "08:00",
    "expected_end_time": "16:30",
    "source": "legacy",
    "first_punch_in": "2026-07-01T15:06:53",
    "last_punch_out": "2026-07-01T16:37:57",
    "total_work_seconds": 5464
  }
]
